{"tokens":[{"type.display.large.mobile":{"value":{"family":{"semantic token":"ouds.font.family.ios.display","core token":"core-ouds.font.family.system.sf-pro","raw value":{"value":{"value":"SF Pro"}}},"letter-spacing":{"semantic token":"ouds.font.letter-spacing.display.large.mobile","core token":"core-ouds.font.letter-spacing.850","raw value":{"value":{"value":"-0.4px"}}},"line-height":{"semantic token":"ouds.font.line-height.display.large.mobile","core token":"core-ouds.font.line-height.1050","raw value":{"value":{"value":"48px"}}},"size":{"semantic token":"ouds.font.size.display.large.mobile","core token":"core-ouds.font.size.850","raw value":{"value":{"value":"40px"}}},"weight":{"semantic token":"ouds.font.weight.ios.display","core token":"core-ouds.font.weight.700","raw value":{"value":{"value":"Bold"}}}}}},{"type.display.medium.mobile":{"value":{"family":{"semantic token":"ouds.font.family.ios.display","core token":"core-ouds.font.family.system.sf-pro","raw value":{"value":{"value":"SF Pro"}}},"letter-spacing":{"semantic token":"ouds.font.letter-spacing.display.medium.mobile","core token":"core-ouds.font.letter-spacing.750","raw value":{"value":{"value":"-0.36px"}}},"line-height":{"semantic token":"ouds.font.line-height.display.medium.mobile","core token":"core-ouds.font.line-height.950","raw value":{"value":{"value":"44px"}}},"size":{"semantic token":"ouds.font.size.display.medium.mobile","core token":"core-ouds.font.size.750","raw value":{"value":{"value":"36px"}}},"weight":{"semantic token":"ouds.font.weight.ios.display","core token":"core-ouds.font.weight.700","raw value":{"value":{"value":"Bold"}}}}}},{"type.display.small.mobile":{"value":{"family":{"semantic token":"ouds.font.family.ios.display","core token":"core-ouds.font.family.system.sf-pro","raw value":{"value":{"value":"SF Pro"}}},"letter-spacing":{"semantic token":"ouds.font.letter-spacing.display.small.mobile","core token":"core-ouds.font.letter-spacing.650","raw value":{"value":{"value":"-0.32px"}}},"line-height":{"semantic token":"ouds.font.line-height.display.small.mobile","core token":"core-ouds.font.line-height.850","raw value":{"value":{"value":"40px"}}},"size":{"semantic token":"ouds.font.size.display.small.mobile","core token":"core-ouds.font.size.650","raw value":{"value":{"value":"32px"}}},"weight":{"semantic token":"ouds.font.weight.ios.display","core token":"core-ouds.font.weight.700","raw value":{"value":{"value":"Bold"}}}}}},{"type.heading.xlarge.mobile":{"value":{"family":{"semantic token":"ouds.font.family.ios.heading","core token":"core-ouds.font.family.system.sf-pro","raw value":{"value":{"value":"SF Pro"}}},"letter-spacing":{"semantic token":"ouds.font.letter-spacing.heading.xlarge.mobile","core token":"core-ouds.font.letter-spacing.550","raw value":{"value":{"value":"-0.28px"}}},"line-height":{"semantic token":"ouds.font.line-height.heading.xlarge.mobile","core token":"core-ouds.font.line-height.750","raw value":{"value":{"value":"36px"}}},"size":{"semantic token":"ouds.font.size.heading.xlarge.mobile","core token":"core-ouds.font.size.550","raw value":{"value":{"value":"28px"}}},"weight":{"semantic token":"ouds.font.weight.ios.heading","core token":"core-ouds.font.weight.700","raw value":{"value":{"value":"Bold"}}}}}},{"type.heading.large.mobile":{"value":{"family":{"semantic token":"ouds.font.family.ios.heading","core token":"core-ouds.font.family.system.sf-pro","raw value":{"value":{"value":"SF Pro"}}},"letter-spacing":{"semantic token":"ouds.font.letter-spacing.heading.large.mobile","core token":"core-ouds.font.letter-spacing.450","raw value":{"value":{"value":"-0.12px"}}},"line-height":{"semantic token":"ouds.font.line-height.heading.large.mobile","core token":"core-ouds.font.line-height.650","raw value":{"value":{"value":"32px"}}},"size":{"semantic token":"ouds.font.size.heading.large.mobile","core token":"core-ouds.font.size.450","raw value":{"value":{"value":"24px"}}},"weight":{"semantic token":"ouds.font.weight.ios.heading","core token":"core-ouds.font.weight.700","raw value":{"value":{"value":"Bold"}}}}}},{"type.heading.medium.mobile":{"value":{"family":{"semantic token":"ouds.font.family.ios.heading","core token":"core-ouds.font.family.system.sf-pro","raw value":{"value":{"value":"SF Pro"}}},"letter-spacing":{"semantic token":"ouds.font.letter-spacing.heading.medium.mobile","core token":"core-ouds.font.letter-spacing.350","raw value":{"value":{"value":"0px"}}},"line-height":{"semantic token":"ouds.font.line-height.heading.medium.mobile","core token":"core-ouds.font.line-height.550","raw value":{"value":{"value":"28px"}}},"size":{"semantic token":"ouds.font.size.heading.medium.mobile","core token":"core-ouds.font.size.350","raw value":{"value":{"value":"20px"}}},"weight":{"semantic token":"ouds.font.weight.ios.heading","core token":"core-ouds.font.weight.700","raw value":{"value":{"value":"Bold"}}}}}},{"type.heading.small.mobile":{"value":{"family":{"semantic token":"ouds.font.family.ios.heading","core token":"core-ouds.font.family.system.sf-pro","raw value":{"value":{"value":"SF Pro"}}},"letter-spacing":{"semantic token":"ouds.font.letter-spacing.heading.small.mobile","core token":"core-ouds.font.letter-spacing.300","raw value":{"value":{"value":"0.18px"}}},"line-height":{"semantic token":"ouds.font.line-height.heading.small.mobile","core token":"core-ouds.font.line-height.450","raw value":{"value":{"value":"24px"}}},"size":{"semantic token":"ouds.font.size.heading.small.mobile","core token":"core-ouds.font.size.300","raw value":{"value":{"value":"18px"}}},"weight":{"semantic token":"ouds.font.weight.ios.heading","core token":"core-ouds.font.weight.700","raw value":{"value":{"value":"Bold"}}}}}},{"type.body.large.mobile":{"value":{"family":{"semantic token":"ouds.font.family.ios.body","core token":"core-ouds.font.family.system.sf-pro","raw value":{"value":{"value":"SF Pro"}}},"letter-spacing":{"semantic token":"ouds.font.letter-spacing.body.large.mobile","core token":"core-ouds.font.letter-spacing.250","raw value":{"value":{"value":"0.2px"}}},"line-height":{"semantic token":"ouds.font.line-height.body.large.mobile","core token":"core-ouds.font.line-height.450","raw value":{"value":{"value":"24px"}}},"size":{"semantic token":"ouds.font.size.body.large.mobile","core token":"core-ouds.font.size.250","raw value":{"value":{"value":"16px"}}},"weight":{"semantic token":"ouds.font.weight.ios.body-strong","core token":"core-ouds.font.weight.700","raw value":{"value":{"value":"Bold"}}}}}},{"type.body.medium.mobile":{"value":{"family":{"semantic token":"ouds.font.family.ios.body","core token":"core-ouds.font.family.system.sf-pro","raw value":{"value":{"value":"SF Pro"}}},"letter-spacing":{"semantic token":"ouds.font.letter-spacing.body.medium.mobile","core token":"core-ouds.font.letter-spacing.200","raw value":{"value":{"value":"0.17px"}}},"line-height":{"semantic token":"ouds.font.line-height.body.medium.mobile","core token":"core-ouds.font.line-height.350","raw value":{"value":{"value":"20px"}}},"size":{"semantic token":"ouds.font.size.body.medium.mobile","core token":"core-ouds.font.size.200","raw value":{"value":{"value":"14px"}}},"weight":{"semantic token":"ouds.font.weight.ios.body-strong","core token":"core-ouds.font.weight.700","raw value":{"value":{"value":"Bold"}}}}}},{"type.body.small.mobile":{"value":{"family":{"semantic token":"ouds.font.family.ios.body","core token":"core-ouds.font.family.system.sf-pro","raw value":{"value":{"value":"SF Pro"}}},"letter-spacing":{"semantic token":"ouds.font.letter-spacing.body.small.mobile","core token":"core-ouds.font.letter-spacing.150","raw value":{"value":{"value":"0.18px"}}},"line-height":{"semantic token":"ouds.font.line-height.body.small.mobile","core token":"core-ouds.font.line-height.250","raw value":{"value":{"value":"16px"}}},"size":{"semantic token":"ouds.font.size.body.small.mobile","core token":"core-ouds.font.size.150","raw value":{"value":{"value":"12px"}}},"weight":{"semantic token":"ouds.font.weight.ios.body-strong","core token":"core-ouds.font.weight.700","raw value":{"value":{"value":"Bold"}}}}}},{"type.label.xlarge":{"value":{"family":{"semantic token":"ouds.font.family.ios.label","core token":"core-ouds.font.family.system.sf-pro","raw value":{"value":{"value":"SF Pro"}}},"letter-spacing":{"semantic token":"ouds.font.letter-spacing.label.xlarge","core token":"core-ouds.font.letter-spacing.300","raw value":{"value":{"value":"0.18px"}}},"line-height":{"semantic token":"ouds.font.line-height.label.xlarge","core token":"core-ouds.font.line-height.450","raw value":{"value":{"value":"24px"}}},"size":{"semantic token":"ouds.font.size.label.xlarge","core token":"core-ouds.font.size.300","raw value":{"value":{"value":"18px"}}},"weight":{"semantic token":"ouds.font.weight.ios.label-strong","core token":"core-ouds.font.weight.700","raw value":{"value":{"value":"Bold"}}}}}},{"type.label.large":{"value":{"family":{"semantic token":"ouds.font.family.ios.label","core token":"core-ouds.font.family.system.sf-pro","raw value":{"value":{"value":"SF Pro"}}},"letter-spacing":{"semantic token":"ouds.font.letter-spacing.label.large","core token":"core-ouds.font.letter-spacing.250","raw value":{"value":{"value":"0.2px"}}},"line-height":{"semantic token":"ouds.font.line-height.label.large","core token":"core-ouds.font.line-height.450","raw value":{"value":{"value":"24px"}}},"size":{"semantic token":"ouds.font.size.label.large","core token":"core-ouds.font.size.250","raw value":{"value":{"value":"16px"}}},"weight":{"semantic token":"ouds.font.weight.ios.label-strong","core token":"core-ouds.font.weight.700","raw value":{"value":{"value":"Bold"}}}}}},{"type.label.medium":{"value":{"family":{"semantic token":"ouds.font.family.ios.label","core token":"core-ouds.font.family.system.sf-pro","raw value":{"value":{"value":"SF Pro"}}},"letter-spacing":{"semantic token":"ouds.font.letter-spacing.label.medium","core token":"core-ouds.font.letter-spacing.200","raw value":{"value":{"value":"0.17px"}}},"line-height":{"semantic token":"ouds.font.line-height.label.medium","core token":"core-ouds.font.line-height.350","raw value":{"value":{"value":"20px"}}},"size":{"semantic token":"ouds.font.size.label.medium","core token":"core-ouds.font.size.200","raw value":{"value":{"value":"14px"}}},"weight":{"semantic token":"ouds.font.weight.ios.label-strong","core token":"core-ouds.font.weight.700","raw value":{"value":{"value":"Bold"}}}}}},{"type.label.small":{"value":{"family":{"semantic token":"ouds.font.family.ios.label","core token":"core-ouds.font.family.system.sf-pro","raw value":{"value":{"value":"SF Pro"}}},"letter-spacing":{"semantic token":"ouds.font.letter-spacing.label.small","core token":"core-ouds.font.letter-spacing.150","raw value":{"value":{"value":"0.18px"}}},"line-height":{"semantic token":"ouds.font.line-height.label.small","core token":"core-ouds.font.line-height.250","raw value":{"value":{"value":"16px"}}},"size":{"semantic token":"ouds.font.size.label.small","core token":"core-ouds.font.size.150","raw value":{"value":{"value":"12px"}}},"weight":{"semantic token":"ouds.font.weight.ios.label-strong","core token":"core-ouds.font.weight.700","raw value":{"value":{"value":"Bold"}}}}}},{"type.code.medium":{"value":{"family":{"semantic token":"ouds.font.family.ios.code","core token":"core-ouds.font.family.monospace.sf-mono","raw value":{"value":{"value":"SF Mono"}}},"letter-spacing":{"semantic token":"ouds.font.letter-spacing.code.medium","core token":"core-ouds.font.letter-spacing.200","raw value":{"value":{"value":"0.17px"}}},"line-height":{"semantic token":"ouds.font.line-height.code.medium","core token":"core-ouds.font.line-height.350","raw value":{"value":{"value":"20px"}}},"size":{"semantic token":"ouds.font.size.code.medium","core token":"core-ouds.font.size.200","raw value":{"value":{"value":"14px"}}},"weight":{"semantic token":"ouds.font.weight.ios.code","core token":"core-ouds.font.weight.400","raw value":{"value":{"value":"Regular"}}}}}}],"versions":{"sys.orange":"1.5.0","core.orange":"1.1.0","core.ouds":"1.5.0"}}